holistic_agent/__init__.py
holistic_agent-0.0.0.dist-info/METADATA
holistic_agent-0.0.0.dist-info/WHEEL
holistic_agent-0.0.0.dist-info/RECORD
